mishmash_rpc_pb2.py
mishmash_rpc_pb2_grpc.py
mishmash_io_rpc-0.0.5.dist-info/LICENSE
mishmash_io_rpc-0.0.5.dist-info/METADATA
mishmash_io_rpc-0.0.5.dist-info/WHEEL
mishmash_io_rpc-0.0.5.dist-info/top_level.txt
mishmash_io_rpc-0.0.5.dist-info/RECORD
